forest_stand_generator_3D/__init__.py
forest_stand_generator_3D/data_validation.py
forest_stand_generator_3D/export.py
forest_stand_generator_3D/stand.py
forest_stand_generator_3D/tree.py
forest_stand_generator_3D/visualization.py
forest_stand_generator_3d-0.1.4.dist-info/licenses/LICENSE
forest_stand_generator_3d-0.1.4.dist-info/METADATA
forest_stand_generator_3d-0.1.4.dist-info/WHEEL
forest_stand_generator_3d-0.1.4.dist-info/top_level.txt
forest_stand_generator_3d-0.1.4.dist-info/RECORD
