Metadata-Version: 2.4
Name: forest-stand-generator-3D
Version: 0.1.4
Summary: A Python package to generate 3D forest stands for radiative transfer and ecological simulations.
Author-email: Prasad Madushanka Dauglas Dambure Liyanage <prasad.dream13@gmail.com>
License: MIT
Project-URL: Homepage, https://github.com/Prasadmadhusanka/Forest-Stand-Generator-3D
Project-URL: Source, https://github.com/Prasadmadhusanka/Forest-Stand-Generator-3D
Project-URL: Issues, https://github.com/Prasadmadhusanka/Forest-Stand-Generator-3D/issues
Keywords: forest,3D,LAI,tree,canopy,simulation
Classifier: Development Status :: 3 - Alpha
Classifier: Intended Audience :: Science/Research
Classifier: License :: OSI Approved :: MIT License
Classifier: Programming Language :: Python :: 3
Classifier: Programming Language :: Python :: 3.10
Classifier: Programming Language :: Python :: 3.11
Classifier: Programming Language :: Python :: 3.12
Classifier: Topic :: Scientific/Engineering
Classifier: Topic :: Scientific/Engineering :: Visualization
Classifier: Topic :: Scientific/Engineering :: Physics
Classifier: Topic :: Scientific/Engineering :: Atmospheric Science
Requires-Python: >=3.10
License-File: LICENSE
Requires-Dist: numpy>=1.24
Requires-Dist: plotly>=5.0
Provides-Extra: dev
Requires-Dist: pytest>=8.0; extra == "dev"
Requires-Dist: black; extra == "dev"
Requires-Dist: mypy; extra == "dev"
Dynamic: license-file
